foocatse/__init__.py
foocatse/foocatse.py
foocatse-0.1.0.dist-info/LICENSE
foocatse-0.1.0.dist-info/WHEEL
foocatse-0.1.0.dist-info/METADATA
foocatse-0.1.0.dist-info/RECORD
